{"id": 448, "name": "Community College Consortium for Open Educational Resources (CCCOER)", "membership_type": "Associate Consortium Members", "membership_status": "Current", "associate_consortium": "", "display_name": "Community College Consortium for Open Educational Resources (CCCOER)", "main_website": "http://oerconsortium.org/", "ocw_website": "", "description": "The Community College Consortium for Open Educational Resources (CCCOER) is a joint effort by the OER Center for California, Foothill-De Anza Community College District, the League for Innovation in the Community College, OCW Consortium and many other community colleges and university partners to develop and use open educational resources (OER) and especially open textbooks in community college courses.", "logo_small": "logos/CCCOER_Logo_small.gif", "logo_small_url": "http://www.ocwconsortium.org/media/logos/CCCOER_Logo_small.gif"}